txquestionnaire/__init__.py
txquestionnaire/questionnaire.tx
textx_lang_questionnaire-0.2.0.dist-info/LICENSE
textx_lang_questionnaire-0.2.0.dist-info/METADATA
textx_lang_questionnaire-0.2.0.dist-info/WHEEL
textx_lang_questionnaire-0.2.0.dist-info/entry_points.txt
textx_lang_questionnaire-0.2.0.dist-info/top_level.txt
textx_lang_questionnaire-0.2.0.dist-info/RECORD
